Metadata-Version: 1.1
Name: codepod
Version: 0.1.0
Summary: Open code workspaces in docker for editing via containerized vscode
Home-page: https://github.com/magland/codepod
Author: Jeremy Magland
Author-email: jmagland@flatironinstitute.org
License: UNKNOWN
Platform: UNKNOWN
Classifier: Programming Language :: Python :: 3
Classifier: License :: OSI Approved :: Apache Software License
Classifier: Operating System :: OS Independent
